README.txt
setup.py
kenfotools/__init__.py
kenfotools/excel.py
kenfotools/file.py
kenfotools.egg-info/PKG-INFO
kenfotools.egg-info/SOURCES.txt
kenfotools.egg-info/dependency_links.txt
kenfotools.egg-info/requires.txt
kenfotools.egg-info/top_level.txt